Metadata-Version: 2.1
Name: deeputils
Version: 2.9.9
Summary: Deepera Development Utils
Home-page: https://github.com/valency/deeputils/
Author: Deepera Co., Ltd.
Author-email: yding@deepera.com
License: UNKNOWN
Keywords: utils,logging
Platform: UNKNOWN
